Metadata-Version: 2.4
Name: iflow-mcp_pubtator-mcp-server
Version: 0.1.1
Summary: A biomedical literature annotation and relationship mining server based on PubTator3
Author-email: JackKuo666 <jack@example.com>
License: MIT
Project-URL: Homepage, https://github.com/JackKuo666/PubTator-MCP-Server
Project-URL: Repository, https://github.com/JackKuo666/PubTator-MCP-Server
Requires-Python: >=3.10
License-File: LICENSE
Requires-Dist: mcp
Requires-Dist: requests
Dynamic: license-file
